[{"date": "2026-03-01", "value": 331.265}, {"date": "2026-02-01", "value": 331.998}, {"date": "2026-01-01", "value": 331.851}, {"date": "2025-12-01", "value": 331.304}, {"date": "2025-11-01", "value": 330.149}, {"date": "2025-10-01", "value": 328.831}, {"date": "2025-09-01", "value": 327.759}, {"date": "2025-08-01", "value": 327.28}, {"date": "2025-07-01", "value": 326.917}, {"date": "2025-06-01", "value": 326.966}, {"date": "2025-05-01", "value": 327.486}, {"date": "2025-04-01", "value": 328.092}, {"date": "2025-03-01", "value": 329.078}, {"date": "2025-02-01", "value": 329.573}, {"date": "2025-01-01", "value": 329.001}, {"date": "2024-12-01", "value": 327.56}, {"date": "2024-11-01", "value": 325.95}, {"date": "2024-10-01", "value": 324.539}, {"date": "2024-09-01", "value": 323.526}, {"date": "2024-08-01", "value": 322.5}, {"date": "2024-07-01", "value": 321.635}, {"date": "2024-06-01", "value": 320.764}, {"date": "2024-05-01", "value": 319.977}, {"date": "2024-04-01", "value": 319.092}, {"date": "2024-03-01", "value": 318.151}, {"date": "2024-02-01", "value": 317.009}, {"date": "2024-01-01", "value": 315.827}, {"date": "2023-12-01", "value": 314.851}, {"date": "2023-11-01", "value": 314.11}, {"date": "2023-10-01", "value": 313.267}, {"date": "2023-09-01", "value": 311.319}, {"date": "2023-08-01", "value": 309.189}, {"date": "2023-07-01", "value": 306.546}, {"date": "2023-06-01", "value": 304.177}, {"date": "2023-05-01", "value": 302.058}, {"date": "2023-04-01", "value": 300.052}, {"date": "2023-03-01", "value": 298.677}, {"date": "2023-02-01", "value": 297.585}, {"date": "2023-01-01", "value": 297.334}, {"date": "2022-12-01", "value": 297.736}, {"date": "2022-11-01", "value": 298.466}, {"date": "2022-10-01", "value": 298.779}, {"date": "2022-09-01", "value": 299.109}, {"date": "2022-08-01", "value": 301.098}, {"date": "2022-07-01", "value": 303.362}, {"date": "2022-06-01", "value": 304.151}, {"date": "2022-05-01", "value": 303.278}, {"date": "2022-04-01", "value": 300.283}, {"date": "2022-03-01", "value": 296.261}, {"date": "2022-02-01", "value": 291.053}, {"date": "2022-01-01", "value": 286.095}, {"date": "2021-12-01", "value": 281.533}, {"date": "2021-11-01", "value": 277.321}, {"date": "2021-10-01", "value": 273.623}, {"date": "2021-09-01", "value": 270.202}, {"date": "2021-08-01", "value": 266.63}, {"date": "2021-07-01", "value": 262.55}, {"date": "2021-06-01", "value": 258.082}, {"date": "2021-05-01", "value": 253.252}, {"date": "2021-04-01", "value": 249.005}, {"date": "2021-03-01", "value": 245.423}, {"date": "2021-02-01", "value": 242.334}, {"date": "2021-01-01", "value": 239.626}, {"date": "2020-12-01", "value": 236.53}, {"date": "2020-11-01", "value": 233.213}, {"date": "2020-10-01", "value": 229.658}, {"date": "2020-09-01", "value": 225.726}, {"date": "2020-08-01", "value": 222.274}, {"date": "2020-07-01", "value": 219.247}, {"date": "2020-06-01", "value": 217.474}, {"date": "2020-05-01", "value": 216.924}, {"date": "2020-04-01", "value": 216.796}, {"date": "2020-03-01", "value": 216.391}, {"date": "2020-02-01", "value": 215.842}, {"date": "2020-01-01", "value": 214.997}, {"date": "2019-12-01", "value": 213.919}, {"date": "2019-11-01", "value": 212.758}, {"date": "2019-10-01", "value": 211.719}, {"date": "2019-09-01", "value": 210.821}, {"date": "2019-08-01", "value": 210.013}, {"date": "2019-07-01", "value": 209.21}, {"date": "2019-06-01", "value": 208.554}, {"date": "2019-05-01", "value": 208.105}, {"date": "2019-04-01", "value": 207.499}, {"date": "2019-03-01", "value": 207.048}, {"date": "2019-02-01", "value": 206.831}, {"date": "2019-01-01", "value": 206.516}, {"date": "2018-12-01", "value": 206.131}, {"date": "2018-11-01", "value": 205.638}, {"date": "2018-10-01", "value": 205.063}, {"date": "2018-09-01", "value": 204.295}, {"date": "2018-08-01", "value": 203.635}, {"date": "2018-07-01", "value": 202.879}, {"date": "2018-06-01", "value": 202.17}, {"date": "2018-05-01", "value": 201.39}, {"date": "2018-04-01", "value": 200.629}, {"date": "2018-03-01", "value": 199.941}, {"date": "2018-02-01", "value": 199.206}, {"date": "2018-01-01", "value": 198.279}, {"date": "2017-12-01", "value": 197.139}, {"date": "2017-11-01", "value": 195.913}, {"date": "2017-10-01", "value": 194.761}, {"date": "2017-09-01", "value": 193.715}, {"date": "2017-08-01", "value": 192.621}, {"date": "2017-07-01", "value": 191.439}, {"date": "2017-06-01", "value": 190.47}, {"date": "2017-05-01", "value": 189.587}, {"date": "2017-04-01", "value": 188.699}, {"date": "2017-03-01", "value": 187.969}, {"date": "2017-02-01", "value": 187.29}, {"date": "2017-01-01", "value": 186.775}, {"date": "2016-12-01", "value": 185.696}, {"date": "2016-11-01", "value": 184.728}, {"date": "2016-10-01", "value": 183.721}, {"date": "2016-09-01", "value": 182.796}, {"date": "2016-08-01", "value": 181.823}, {"date": "2016-07-01", "value": 180.838}, {"date": "2016-06-01", "value": 180.064}, {"date": "2016-05-01", "value": 179.401}, {"date": "2016-04-01", "value": 178.742}, {"date": "2016-03-01", "value": 178.142}, {"date": "2016-02-01", "value": 177.625}, {"date": "2016-01-01", "value": 177.244}, {"date": "2015-12-01", "value": 176.517}, {"date": "2015-11-01", "value": 175.708}, {"date": "2015-10-01", "value": 174.764}, {"date": "2015-09-01", "value": 173.8}, {"date": "2015-08-01", "value": 172.908}, {"date": "2015-07-01", "value": 172.131}, {"date": "2015-06-01", "value": 171.454}, {"date": "2015-05-01", "value": 170.862}, {"date": "2015-04-01", "value": 170.278}, {"date": "2015-03-01", "value": 169.777}, {"date": "2015-02-01", "value": 169.105}, {"date": "2015-01-01", "value": 168.612}, {"date": "2014-12-01", "value": 168.037}, {"date": "2014-11-01", "value": 167.321}, {"date": "2014-10-01", "value": 166.626}, {"date": "2014-09-01", "value": 165.888}, {"date": "2014-08-01", "value": 165.197}, {"date": "2014-07-01", "value": 164.572}, {"date": "2014-06-01", "value": 164.047}, {"date": "2014-05-01", "value": 163.641}, {"date": "2014-04-01", "value": 163.376}, {"date": "2014-03-01", "value": 163.074}, {"date": "2014-02-01", "value": 162.516}, {"date": "2014-01-01", "value": 161.92}, {"date": "2013-12-01", "value": 160.991}, {"date": "2013-11-01", "value": 160.07}, {"date": "2013-10-01", "value": 159.234}, {"date": "2013-09-01", "value": 158.215}, {"date": "2013-08-01", "value": 156.951}, {"date": "2013-07-01", "value": 155.596}, {"date": "2013-06-01", "value": 154.19}, {"date": "2013-05-01", "value": 152.84}, {"date": "2013-04-01", "value": 151.508}, {"date": "2013-03-01", "value": 149.951}, {"date": "2013-02-01", "value": 147.772}, {"date": "2013-01-01", "value": 146.816}, {"date": "2012-12-01", "value": 145.492}, {"date": "2012-11-01", "value": 144.575}, {"date": "2012-10-01", "value": 143.591}, {"date": "2012-09-01", "value": 142.898}, {"date": "2012-08-01", "value": 142.269}, {"date": "2012-07-01", "value": 141.66}, {"date": "2012-06-01", "value": 141.019}, {"date": "2012-05-01", "value": 140.144}, {"date": "2012-04-01", "value": 139.144}, {"date": "2012-03-01", "value": 137.893}, {"date": "2012-02-01", "value": 136.522}, {"date": "2012-01-01", "value": 136.595}, {"date": "2011-12-01", "value": 136.66}, {"date": "2011-11-01", "value": 137.137}, {"date": "2011-10-01", "value": 137.94}, {"date": "2011-09-01", "value": 138.659}, {"date": "2011-08-01", "value": 139.303}, {"date": "2011-07-01", "value": 139.727}, {"date": "2011-06-01", "value": 139.858}, {"date": "2011-05-01", "value": 139.901}, {"date": "2011-04-01", "value": 140.003}, {"date": "2011-03-01", "value": 139.971}, {"date": "2011-02-01", "value": 140.338}, {"date": "2011-01-01", "value": 141.511}, {"date": "2010-12-01", "value": 142.049}, {"date": "2010-11-01", "value": 142.163}, {"date": "2010-10-01", "value": 142.523}, {"date": "2010-09-01", "value": 143.013}, {"date": "2010-08-01", "value": 143.91}, {"date": "2010-07-01", "value": 144.984}, {"date": "2010-06-01", "value": 145.714}, {"date": "2010-05-01", "value": 146.386}, {"date": "2010-04-01", "value": 146.398}, {"date": "2010-03-01", "value": 145.857}, {"date": "2010-02-01", "value": 145.632}, {"date": "2010-01-01", "value": 147.396}, {"date": "2009-12-01", "value": 147.931}, {"date": "2009-11-01", "value": 148.136}, {"date": "2009-10-01", "value": 147.85}, {"date": "2009-09-01", "value": 148.024}, {"date": "2009-08-01", "value": 148.276}, {"date": "2009-07-01", "value": 148.407}, {"date": "2009-06-01", "value": 148.087}, {"date": "2009-05-01", "value": 147.693}, {"date": "2009-04-01", "value": 147.948}, {"date": "2009-03-01", "value": 148.659}, {"date": "2009-02-01", "value": 150.013}, {"date": "2009-01-01", "value": 151.506}, {"date": "2008-12-01", "value": 153.617}, {"date": "2008-11-01", "value": 156.14}, {"date": "2008-10-01", "value": 158.325}, {"date": "2008-09-01", "value": 160.306}, {"date": "2008-08-01", "value": 161.985}, {"date": "2008-07-01", "value": 163.563}, {"date": "2008-06-01", "value": 165.014}, {"date": "2008-05-01", "value": 166.654}, {"date": "2008-04-01", "value": 168.333}, {"date": "2008-03-01", "value": 170.05}, {"date": "2008-02-01", "value": 171.539}, {"date": "2008-01-01", "value": 173.131}, {"date": "2007-12-01", "value": 174.34}, {"date": "2007-11-01", "value": 175.146}, {"date": "2007-10-01", "value": 176.623}, {"date": "2007-09-01", "value": 177.556}, {"date": "2007-08-01", "value": 178.115}, {"date": "2007-07-01", "value": 179.109}, {"date": "2007-06-01", "value": 180.253}, {"date": "2007-05-01", "value": 181.6}, {"date": "2007-04-01", "value": 183.009}, {"date": "2007-03-01", "value": 184.148}, {"date": "2007-02-01", "value": 184.596}, {"date": "2007-01-01", "value": 184.515}, {"date": "2006-12-01", "value": 184.137}, {"date": "2006-11-01", "value": 183.608}, {"date": "2006-10-01", "value": 183.198}, {"date": "2006-09-01", "value": 182.798}, {"date": "2006-08-01", "value": 182.593}, {"date": "2006-07-01", "value": 183.068}, {"date": "2006-06-01", "value": 183.508}, {"date": "2006-05-01", "value": 184.157}, {"date": "2006-04-01", "value": 184.33}, {"date": "2006-03-01", "value": 184.365}, {"date": "2006-02-01", "value": 183.288}, {"date": "2006-01-01", "value": 182.322}, {"date": "2005-12-01", "value": 180.912}, {"date": "2005-11-01", "value": 179.684}, {"date": "2005-10-01", "value": 178.03}, {"date": "2005-09-01", "value": 176.44}, {"date": "2005-08-01", "value": 174.443}, {"date": "2005-07-01", "value": 172.861}, {"date": "2005-06-01", "value": 171.192}, {"date": "2005-05-01", "value": 169.353}, {"date": "2005-04-01", "value": 167.504}, {"date": "2005-03-01", "value": 165.815}, {"date": "2005-02-01", "value": 163.346}, {"date": "2005-01-01", "value": 161.289}, {"date": "2004-12-01", "value": 159.33}, {"date": "2004-11-01", "value": 157.527}, {"date": "2004-10-01", "value": 155.75}, {"date": "2004-09-01", "value": 154.179}, {"date": "2004-08-01", "value": 152.633}, {"date": "2004-07-01", "value": 151.338}, {"date": "2004-06-01", "value": 149.851}, {"date": "2004-05-01", "value": 148.186}, {"date": "2004-04-01", "value": 146.593}, {"date": "2004-03-01", "value": 145.059}, {"date": "2004-02-01", "value": 143.191}, {"date": "2004-01-01", "value": 141.647}, {"date": "2003-12-01", "value": 140.182}, {"date": "2003-11-01", "value": 138.795}, {"date": "2003-10-01", "value": 137.533}, {"date": "2003-09-01", "value": 136.295}, {"date": "2003-08-01", "value": 134.968}, {"date": "2003-07-01", "value": 133.777}, {"date": "2003-06-01", "value": 132.649}, {"date": "2003-05-01", "value": 131.735}, {"date": "2003-04-01", "value": 130.884}, {"date": "2003-03-01", "value": 130.148}, {"date": "2003-02-01", "value": 129.357}, {"date": "2003-01-01", "value": 128.462}, {"date": "2002-12-01", "value": 127.625}, {"date": "2002-11-01", "value": 126.671}, {"date": "2002-10-01", "value": 125.736}, {"date": "2002-09-01", "value": 124.781}, {"date": "2002-08-01", "value": 123.832}, {"date": "2002-07-01", "value": 122.888}, {"date": "2002-06-01", "value": 121.814}, {"date": "2002-05-01", "value": 120.725}, {"date": "2002-04-01", "value": 119.611}, {"date": "2002-03-01", "value": 118.688}, {"date": "2002-02-01", "value": 117.845}, {"date": "2002-01-01", "value": 117.142}, {"date": "2001-12-01", "value": 116.454}, {"date": "2001-11-01", "value": 115.857}, {"date": "2001-10-01", "value": 115.31}, {"date": "2001-09-01", "value": 114.813}, {"date": "2001-08-01", "value": 114.169}, {"date": "2001-07-01", "value": 113.493}, {"date": "2001-06-01", "value": 112.796}, {"date": "2001-05-01", "value": 112.164}, {"date": "2001-04-01", "value": 111.653}, {"date": "2001-03-01", "value": 111.11}, {"date": "2001-02-01", "value": 110.502}, {"date": "2001-01-01", "value": 109.848}, {"date": "2000-12-01", "value": 109.143}, {"date": "2000-11-01", "value": 108.303}, {"date": "2000-10-01", "value": 107.384}, {"date": "2000-09-01", "value": 106.539}, {"date": "2000-08-01", "value": 105.769}, {"date": "2000-07-01", "value": 105.055}, {"date": "2000-06-01", "value": 104.424}, {"date": "2000-05-01", "value": 103.677}, {"date": "2000-04-01", "value": 102.922}, {"date": "2000-03-01", "value": 102.127}, {"date": "2000-02-01", "value": 101.339}, {"date": "2000-01-01", "value": 100.551}, {"date": "1999-12-01", "value": 99.843}, {"date": "1999-11-01", "value": 99.153}, {"date": "1999-10-01", "value": 98.521}, {"date": "1999-09-01", "value": 97.861}, {"date": "1999-08-01", "value": 97.217}, {"date": "1999-07-01", "value": 96.59}, {"date": "1999-06-01", "value": 95.974}, {"date": "1999-05-01", "value": 95.344}, {"date": "1999-04-01", "value": 94.785}, {"date": "1999-03-01", "value": 94.216}, {"date": "1999-02-01", "value": 93.671}, {"date": "1999-01-01", "value": 93.206}, {"date": "1998-12-01", "value": 92.711}, {"date": "1998-11-01", "value": 92.198}, {"date": "1998-10-01", "value": 91.715}, {"date": "1998-09-01", "value": 91.257}, {"date": "1998-08-01", "value": 90.784}, {"date": "1998-07-01", "value": 90.308}, {"date": "1998-06-01", "value": 89.843}, {"date": "1998-05-01", "value": 89.364}, {"date": "1998-04-01", "value": 88.878}, {"date": "1998-03-01", "value": 88.442}, {"date": "1998-02-01", "value": 88.005}, {"date": "1998-01-01", "value": 87.616}, {"date": "1997-12-01", "value": 87.093}, {"date": "1997-11-01", "value": 86.633}, {"date": "1997-10-01", "value": 86.147}, {"date": "1997-09-01", "value": 85.85}, {"date": "1997-08-01", "value": 85.573}, {"date": "1997-07-01", "value": 85.331}, {"date": "1997-06-01", "value": 85.079}, {"date": "1997-05-01", "value": 84.86}, {"date": "1997-04-01", "value": 84.621}, {"date": "1997-03-01", "value": 84.449}, {"date": "1997-02-01", "value": 84.18}, {"date": "1997-01-01", "value": 83.954}, {"date": "1996-12-01", "value": 83.72}, {"date": "1996-11-01", "value": 83.551}, {"date": "1996-10-01", "value": 83.376}, {"date": "1996-09-01", "value": 83.255}, {"date": "1996-08-01", "value": 83.085}, {"date": "1996-07-01", "value": 82.927}, {"date": "1996-06-01", "value": 82.751}, {"date": "1996-05-01", "value": 82.607}, {"date": "1996-04-01", "value": 82.419}, {"date": "1996-03-01", "value": 82.194}, {"date": "1996-02-01", "value": 81.954}, {"date": "1996-01-01", "value": 81.833}, {"date": "1995-12-01", "value": 81.735}, {"date": "1995-11-01", "value": 81.616}, {"date": "1995-10-01", "value": 81.48}, {"date": "1995-09-01", "value": 81.304}, {"date": "1995-08-01", "value": 81.11}, {"date": "1995-07-01", "value": 80.937}, {"date": "1995-06-01", "value": 80.785}, {"date": "1995-05-01", "value": 80.703}, {"date": "1995-04-01", "value": 80.66}, {"date": "1995-03-01", "value": 80.596}, {"date": "1995-02-01", "value": 80.528}, {"date": "1995-01-01", "value": 80.424}, {"date": "1994-12-01", "value": 80.295}, {"date": "1994-11-01", "value": 80.147}, {"date": "1994-10-01", "value": 80.064}, {"date": "1994-09-01", "value": 79.918}, {"date": "1994-08-01", "value": 79.78}, {"date": "1994-07-01", "value": 79.595}, {"date": "1994-06-01", "value": 79.422}, {"date": "1994-05-01", "value": 79.221}, {"date": "1994-04-01", "value": 78.987}, {"date": "1994-03-01", "value": 78.855}, {"date": "1994-02-01", "value": 78.726}, {"date": "1994-01-01", "value": 78.59}, {"date": "1993-12-01", "value": 78.327}, {"date": "1993-11-01", "value": 78.145}, {"date": "1993-10-01", "value": 77.944}, {"date": "1993-09-01", "value": 77.796}, {"date": "1993-08-01", "value": 77.614}, {"date": "1993-07-01", "value": 77.432}, {"date": "1993-06-01", "value": 77.242}, {"date": "1993-05-01", "value": 77.037}, {"date": "1993-04-01", "value": 76.936}, {"date": "1993-03-01", "value": 76.867}, {"date": "1993-02-01", "value": 76.837}, {"date": "1993-01-01", "value": 76.783}, {"date": "1992-12-01", "value": 76.675}, {"date": "1992-11-01", "value": 76.552}, {"date": "1992-10-01", "value": 76.378}, {"date": "1992-09-01", "value": 76.239}, {"date": "1992-08-01", "value": 76.231}, {"date": "1992-07-01", "value": 76.267}, {"date": "1992-06-01", "value": 76.331}, {"date": "1992-05-01", "value": 76.398}, {"date": "1992-04-01", "value": 76.346}, {"date": "1992-03-01", "value": 76.278}, {"date": "1992-02-01", "value": 76.158}, {"date": "1992-01-01", "value": 76.087}, {"date": "1991-12-01", "value": 76.051}, {"date": "1991-11-01", "value": 76.003}, {"date": "1991-10-01", "value": 76.074}, {"date": "1991-09-01", "value": 76.192}, {"date": "1991-08-01", "value": 76.104}, {"date": "1991-07-01", "value": 76.08}, {"date": "1991-06-01", "value": 75.992}, {"date": "1991-05-01", "value": 75.761}, {"date": "1991-04-01", "value": 75.564}, {"date": "1991-03-01", "value": 75.564}, {"date": "1991-02-01", "value": 75.732}, {"date": "1991-01-01", "value": 75.913}, {"date": "1990-12-01", "value": 76.184}, {"date": "1990-11-01", "value": 76.361}, {"date": "1990-10-01", "value": 76.703}, {"date": "1990-09-01", "value": 76.849}, {"date": "1990-08-01", "value": 77.008}, {"date": "1990-07-01", "value": 77.142}, {"date": "1990-06-01", "value": 77.258}, {"date": "1990-05-01", "value": 77.298}, {"date": "1990-04-01", "value": 77.277}, {"date": "1990-03-01", "value": 77.2}, {"date": "1990-02-01", "value": 77.052}, {"date": "1990-01-01", "value": 76.897}, {"date": "1989-12-01", "value": 76.704}, {"date": "1989-11-01", "value": 76.512}, {"date": "1989-10-01", "value": 76.284}, {"date": "1989-09-01", "value": 76.054}, {"date": "1989-08-01", "value": 75.833}, {"date": "1989-07-01", "value": 75.658}, {"date": "1989-06-01", "value": 75.477}, {"date": "1989-05-01", "value": 75.304}, {"date": "1989-04-01", "value": 75.082}, {"date": "1989-03-01", "value": 74.777}, {"date": "1989-02-01", "value": 74.381}, {"date": "1989-01-01", "value": 73.946}, {"date": "1988-12-01", "value": 73.464}, {"date": "1988-11-01", "value": 73.067}, {"date": "1988-10-01", "value": 72.638}, {"date": "1988-09-01", "value": 72.241}, {"date": "1988-08-01", "value": 71.8}, {"date": "1988-07-01", "value": 71.355}, {"date": "1988-06-01", "value": 70.888}, {"date": "1988-05-01", "value": 70.426}, {"date": "1988-04-01", "value": 69.976}, {"date": "1988-03-01", "value": 69.639}, {"date": "1988-02-01", "value": 69.264}, {"date": "1988-01-01", "value": 68.859}, {"date": "1987-12-01", "value": 68.506}, {"date": "1987-11-01", "value": 68.104}, {"date": "1987-10-01", "value": 67.74}, {"date": "1987-09-01", "value": 67.33}, {"date": "1987-08-01", "value": 66.939}, {"date": "1987-07-01", "value": 66.507}, {"date": "1987-06-01", "value": 66.07}, {"date": "1987-05-01", "value": 65.562}, {"date": "1987-04-01", "value": 65.129}, {"date": "1987-03-01", "value": 64.732}, {"date": "1987-02-01", "value": 64.421}, {"date": "1987-01-01", "value": 63.963}]